g2b/__init__.py
g2b/g2b.py
g2b-0.2.1.dist-info/licenses/LICENSE
g2b-0.2.1.dist-info/METADATA
g2b-0.2.1.dist-info/WHEEL
g2b-0.2.1.dist-info/entry_points.txt
g2b-0.2.1.dist-info/top_level.txt
g2b-0.2.1.dist-info/RECORD
