Metadata-Version: 2.4
Name: g2b
Version: 0.2.1
Summary: Initialize a beancount ledger from a GnuCash file
License: MIT License
Project-URL: Homepage, https://github.com/dtrai2/gnucash-csv-to-beancount
Project-URL: Documentation, https://github.com/dtrai2/gnucash-csv-to-beancount/blob/main/README.md
Project-URL: Repository, https://github.com/dtrai2/gnucash-csv-to-beancount
Project-URL: Issues, https://github.com/dtrai2/gnucash-csv-to-beancount/issues
Keywords: gnucash,beancount,finance,accounting
Classifier: Development Status :: 3 - Alpha
Classifier: License :: OSI Approved :: MIT License
Classifier: Programming Language :: Python
Classifier: Programming Language :: Python :: 3
Classifier: Programming Language :: Python :: 3.10
Classifier: Programming Language :: Python :: 3.11
Classifier: Topic :: Office/Business :: Financial :: Accounting
Requires-Python: >=3.10
License-File: LICENSE
Requires-Dist: beancount
Requires-Dist: click
Requires-Dist: rich
Requires-Dist: pyyaml
Requires-Dist: piecash
Provides-Extra: dev
Requires-Dist: black; extra == "dev"
Requires-Dist: pylint; extra == "dev"
Requires-Dist: pytest; extra == "dev"
Requires-Dist: pytest-cov; extra == "dev"
Requires-Dist: coverage; extra == "dev"
Requires-Dist: ruff; extra == "dev"
Requires-Dist: pre-commit; extra == "dev"
Dynamic: license-file
